demo.py
run_unimernet_app.py
test.py
train.py
unimernet/__init__.py
unimernet/common/__init__.py
unimernet/common/config.py
unimernet/common/dist_utils.py
unimernet/common/gradcam.py
unimernet/common/logger.py
unimernet/common/optims.py
unimernet/common/registry.py
unimernet/common/utils.py
unimernet/configs/datasets/formula/formula_eval.yaml
unimernet/configs/datasets/formula/formula_train.yaml
unimernet/configs/datasets/formula/multi_scale_formula_train.yaml
unimernet/configs/default.yaml
unimernet/configs/models/unimernet_base.yaml
unimernet/datasets/__init__.py
unimernet/datasets/builders/__init__.py
unimernet/datasets/builders/base_dataset_builder.py
unimernet/datasets/builders/formula.py
unimernet/datasets/data_utils.py
unimernet/datasets/datasets/base_dataset.py
unimernet/datasets/datasets/dataloader_utils.py
unimernet/datasets/datasets/formula.py
unimernet/datasets/datasets/formula_multi_scale.py
unimernet/models/__init__.py
unimernet/models/base_model.py
unimernet/models/blip2_models/Qformer.py
unimernet/models/blip2_models/__init__.py
unimernet/models/blip2_models/blip2.py
unimernet/models/blip2_models/blip2_vicuna_instruct.py
unimernet/models/blip2_models/modeling_llama.py
unimernet/models/blip2_models/modeling_llama_.py
unimernet/models/clip_vit.py
unimernet/models/eva_vit.py
unimernet/models/unimernet/__init__.py
unimernet/models/unimernet/configuration_unimernet_decoder.py
unimernet/models/unimernet/configuration_unimernet_encoder.py
unimernet/models/unimernet/encoder_decoder.py
unimernet/models/unimernet/modeling_unimernet_decoder.py
unimernet/models/unimernet/modeling_unimernet_encoder.py
unimernet/models/unimernet/processor.py
unimernet/models/unimernet/unimernet.py
unimernet/models/unimernet/utils.py
unimernet/models/vit.py
unimernet/processors/__init__.py
unimernet/processors/base_processor.py
unimernet/processors/blip_processors.py
unimernet/processors/formula_processor.py
unimernet/processors/formula_processor_helper/__init__.py
unimernet-0.2.3.dist-info/LICENSE
unimernet-0.2.3.dist-info/METADATA
unimernet-0.2.3.dist-info/WHEEL
unimernet-0.2.3.dist-info/entry_points.txt
unimernet-0.2.3.dist-info/RECORD
