Metadata-Version: 2.1
Name: unimernet
Version: 0.2.3
Summary: UniMERNet: A Universal Network for Real-World Mathematical Expression Recognition
Home-page: https://github.com/opendatalab/UniMERNet
License: Apache-2.0
Keywords: MER,latex,markdown,pdf
Author: Bin Wang
Author-email: ictwangbin@gmail.com
Requires-Python: >=3.10
Classifier: License :: OSI Approved :: Apache Software License
Classifier: Programming Language :: Python :: 3
Classifier: Programming Language :: Python :: 3.10
Classifier: Programming Language :: Python :: 3.11
Classifier: Programming Language :: Python :: 3.12
Provides-Extra: full
Requires-Dist: albumentations (>=1.4.4,<2.0.0)
Requires-Dist: evaluate (>=0.4.1,<0.5.0)
Requires-Dist: fairscale (>=0.4.13,<0.5.0)
Requires-Dist: ftfy (>=6.2.0,<7.0.0) ; python_version >= "3.10" and python_version < "4.0"
Requires-Dist: iopath (>=0.1.9,<0.2.0)
Requires-Dist: jupyterlab (>=4.1.6,<5.0.0) ; extra == "full"
Requires-Dist: matplotlib (>=3.8.4,<4.0.0)
Requires-Dist: nltk (>=3.8.1,<4.0.0) ; extra == "full"
Requires-Dist: omegaconf (>=2.3.0,<3.0.0)
Requires-Dist: opencv-python (>=4.6.0,<5.0.0)
Requires-Dist: pandas (>=2.2.2,<3.0.0) ; extra == "full"
Requires-Dist: pdf2image (>=1.17.0,<2.0.0) ; extra == "full"
Requires-Dist: pypdfium2 (>=4.29.0,<5.0.0) ; extra == "full"
Requires-Dist: rapidfuzz (>=3.8.1,<4.0.0)
Requires-Dist: rich (>=13.7.1,<14.0.0) ; extra == "full"
Requires-Dist: streamlit (>=1.33.0,<2.0.0) ; extra == "full"
Requires-Dist: streamlit_drawable_canvas (>=0.9.3,<0.10.0) ; extra == "full"
Requires-Dist: tabulate (>=0.9.0,<0.10.0) ; extra == "full"
Requires-Dist: termcolor (>=2.4.0,<3.0.0) ; extra == "full"
Requires-Dist: timm (>=0.9.16,<0.10.0)
Requires-Dist: torch (>=2.2.2)
Requires-Dist: torchvision (>=0.17.2)
Requires-Dist: transformers (==4.42.4)
Requires-Dist: wand (>=0.6.13,<0.7.0)
Requires-Dist: webdataset (>=0.2.86,<0.3.0)
Project-URL: Repository, https://github.com/opendatalab/UniMERNet
